{
  "db_name": "PostgreSQL",
  "query": "INSERT INTO workouts (date, muscle_group, notes, user_id) VALUES ($1, $2, $3, $4) RETURNING *",
  "describe": {
    "columns": [
      {
        "ordinal": 0,
        "name": "id",
        "type_info": "Int8"
      },
      {
        "ordinal": 1,
        "name": "date",
        "type_info": "Text"
      },
      {
        "ordinal": 2,
        "name": "muscle_group",
        "type_info": "Text"
      },
      {
        "ordinal": 3,
        "name": "notes",
        "type_info": "Text"
      },
      {
        "ordinal": 4,
        "name": "user_id",
        "type_info": "Int8"
      }
    ],
    "parameters": {
      "Left": [
        "Text",
        "Text",
        "Text",
        "Int8"
      ]
    },
    "nullable": [
      false,
      false,
      false,
      true,
      false
    ]
  },
  "hash": "8eda486e26e008ab1f4c19706e8d2cc44774c95a2a623334056092a68b8ccc51"
}
